<annotation>
	<folder>train</folder>
	<filename>small_screw_5_171.jpg</filename>
	<path>C:\Users\emb-ashwcho\obj_dec\models-master\research\object_detection\images\train\small_screw_5_171.jpg</path>
	<source>
		<database>Unknown</database>
	</source>
	<size>
		<width>800</width>
		<height>600</height>
		<depth>3</depth>
	</size>
	<segmented>0</segmented>
	<object>
		<name>smallscrew</name>
		<pose>Unspecified</pose>
		<truncated>0</truncated>
		<difficult>0</difficult>
		<bndbox>
			<xmin>125</xmin>
			<ymin>115</ymin>
			<xmax>701</xmax>
			<ymax>487</ymax>
		</bndbox>
	</object>
</annotation>
